README.md
setup.py
neopylib/Matching.py
neopylib/__init__.py
neopylib.egg-info/PKG-INFO
neopylib.egg-info/SOURCES.txt
neopylib.egg-info/dependency_links.txt
neopylib.egg-info/top_level.txt
neopylib/Constraints/Constraints.py
neopylib/Constraints/Helpers.py
neopylib/Constraints/__init__.py
neopylib/Entities/Functions.py
neopylib/Entities/GraphEntities.py
neopylib/Entities/__init__.py