Metadata-Version: 2.1
Name: neopylib
Version: 0.2.0
Summary: A pythonic Cypher queries generator
Home-page: https://github.com/intv0id/neopylib
Author: Clément Trassoudaine
Author-email: clement.trassoudaine@eurecom.fr
License: MIT
Keywords: neo4j cypher graph
Platform: UNKNOWN
Classifier: Programming Language :: Python :: 3
Classifier: License :: OSI Approved :: MIT License
Classifier: Operating System :: OS Independent
Requires-Python: >=3.6.6
